{"phoneDetails":{"customId":944394,"yearValue":"2022","brandValue":"Apple","modelValue":"iPad (2022)"},"gsmNetworkDetails":{"networkTechnology":"GSM / HSPA / LTE / 5G","network2GBands":"GSM 850 / 900 / 1800 / 1900","network3GBands":"HSDPA 850 / 900 / 1700(AWS) / 1900 / 2100 - A2757","network4GBands":"1, 2, 3, 4, 5, 7, 8, 11, 12, 13, 14, 17, 18, 19, 20, 21, 25, 26, 28, 29, 30, 32, 34, 38, 39, 40, 41, 42, 46, 48, 66, 71 - A2757\\n1, 2, 3, 4, 5, 7, 8, 12, 13, 14, 17, 18, 19, 20, 25, 26, 28, 29, 30, 32, 34, 38, 39, 40, 41, 42, 46, 48, 66, 71 - A2777","network5GBands":"1, 2, 3, 5, 7, 8, 12, 20, 25, 28, 29, 30, 38, 40, 41, 48, 66, 71, 77, 78, 79 SA/NSA/Sub6 - A2757, A2777","networkSpeed":"HSPA, LTE-A, 5G"},"gsmLaunchDetails":{"launchAnnounced":"2022, October 18","launchStatus":"Available. Released 2022, October 26"},"gsmBodyDetails":{"bodyDimensions":"248.6 x 179.5 x 7 mm (9.79 x 7.07 x 0.28 in)","bodyWeight":"477 g (Wi-Fi) / 481 g (LTE) (1.05 lb)","bodySim":"Nano-SIM and eSIM","bodyBuild":"Glass front, aluminum back, aluminum frame","bodyOther1":"Stylus support (1st gen only)"},"gsmDisplayDetails":{"displayType":"Liquid Retina IPS LCD, 500 nits (typ)","displaySize":"10.9 inches, 359.2 cm2 (~80.5% screen-to-body ratio)","displayResolution":"1640 x 2360 pixels (~264 ppi density)","displayProtection":"Scratch-resistant glass, oleophobic coating"},"gsmPlatformDetails":{"platformChipset":"Apple A14 Bionic (5 nm)","platformCpu":"Hexa-core (2x3.0 GHz Firestorm + 4x1.8 GHz Icestorm)","platformGpu":"Apple GPU (4-core graphics)","platformOs":"iPadOS 16.1"},"gsmMemoryDetails":{"memoryCardSlot":"No","memoryInternal":"64GB, 256GB"},"gsmMainCameraDetails":{"mainCameraFeatures":"HDR, panorama","mainCameraSingle":"12 MP, f/1.8, (wide), PDAF","mainCameraVideo":"4K@24/25/30/60fps, 1080p@25/30/60/120/240fps"},"gsmSelfieCameraDetails":{"selfieCameraFeatures":"HDR","selfieCameraSingle":"12 MP, f/2.4, 122˚ (ultrawide)","selfieCameraVideo":"1080p@25/30/60fps, gyro-EIS"},"gsmSoundDetails":{"sound35MmJack":"No","soundLoudspeaker":"Yes, with stereo speakers"},"gsmCommunicationsDetails":{"communicationsBluetooth":"5.2, A2DP, EDR, LE","communicationsNfc":"No","communicationsPositioning":"GPS, GLONASS (Wi‑Fi + Cellular model only)","communicationsRadio":"No","communicationsUsb":"USB Type-C 2.0, DisplayPort; magnetic connector","communicationsWlan":"Wi-Fi 802.11 a/b/g/n/ac/6, dual-band, hotspot"},"gsmFeaturesDetails":[],"gsmBatteryDetails":{"batteryType":"Li-Ion, non-removable (28.6 Wh)"},"gsmMiscDetails":{"miscColors":"Silver, Blue, Pink, Yellow","miscModels":"A2757, A2777","miscPrice":"About 580 EUR"},"gsmTestsDetails":[]}